[
  {
    "name": "星屑ビーナス",
    "artist": "Aimer",
    "album": "Sleepless Nights",
    "nowplaying": false,
    "ts": "1778426266"
  },
  {
    "name": "ただ君に晴れ",
    "artist": "ヨルシカ",
    "album": "負け犬にアンコールはいらない",
    "nowplaying": false,
    "ts": "1778426067"
  },
  {
    "name": "キラメキ",
    "artist": "wacci",
    "album": "日常ドラマチック",
    "nowplaying": false,
    "ts": "1778425782"
  },
  {
    "name": "青のすみか",
    "artist": "Tatsuya Kitani",
    "album": "ROUNDABOUT",
    "nowplaying": false,
    "ts": "1778415265"
  },
  {
    "name": "逆夢",
    "artist": "King Gnu",
    "album": "逆夢",
    "nowplaying": false,
    "ts": "1778414958"
  },
  {
    "name": "Anytime Anywhere",
    "artist": "Milet",
    "album": "Anytime Anywhere",
    "nowplaying": false,
    "ts": "1778414765"
  }
]