[
  {
    "name": "ただ君に晴れ",
    "artist": "ヨルシカ",
    "album": "負け犬にアンコールはいらない",
    "nowplaying": false,
    "ts": "1783043049"
  },
  {
    "name": "明日への手紙(ドラマバージョン)",
    "artist": "手嶌葵",
    "album": "Highlights from Aoi Works",
    "nowplaying": false,
    "ts": "1783042731"
  },
  {
    "name": "Pretender",
    "artist": "Official鬍子男dism",
    "album": "Traveler",
    "nowplaying": false,
    "ts": "1783042404"
  },
  {
    "name": "Shukumei",
    "artist": "Official HIGE DANdism",
    "album": "Traveler",
    "nowplaying": false,
    "ts": "1783007035"
  },
  {
    "name": "群青",
    "artist": "YOASOBI",
    "album": "THE BOOK",
    "nowplaying": false,
    "ts": "1783004727"
  },
  {
    "name": "失恋ソング沢山聴いて 泣いてばかりの私はもう。 - acoustic ver.",
    "artist": "riria.",
    "album": "軌跡",
    "nowplaying": false,
    "ts": "1783004440"
  }
]