[
  {
    "name": "Avid",
    "artist": "澤野弘之",
    "album": "PIANOUTA",
    "nowplaying": false,
    "ts": "1780221036"
  },
  {
    "name": "「悲しみは水のよう」《我的悲伤是水做的》日文版",
    "artist": "夏野Natsuno",
    "album": "「悲しみは水のよう」《我的悲伤是水做的》日文版",
    "nowplaying": false,
    "ts": "1780220807"
  },
  {
    "name": "たぶん",
    "artist": "YOASOBI",
    "album": "たぶん",
    "nowplaying": false,
    "ts": "1780220548"
  },
  {
    "name": "所念皆星河",
    "artist": "房東的貓",
    "album": "所念皆星河",
    "nowplaying": false,
    "ts": "1780220303"
  },
  {
    "name": "ヒッチコック",
    "artist": "ヨルシカ",
    "album": "負け犬にアンコールはいらない",
    "nowplaying": false,
    "ts": "1780220080"
  },
  {
    "name": "ただ君に晴れ",
    "artist": "ヨルシカ",
    "album": "負け犬にアンコールはいらない",
    "nowplaying": false,
    "ts": "1780219880"
  }
]