{
  "bookmarks": [
    {
      "title": "sambecker/exif-photo-blog: Photo blog, reporting 🤓 EXIF camera details (aperture, shutter speed, ISO) for each image.",
      "link": "https://github.com/sambecker/exif-photo-blog",
      "domain": "github.com",
      "tags": [],
      "note": "",
      "excerpt": "Photo blog, reporting 🤓 EXIF camera details (aperture, shutter speed, ISO) for each image. - sambecker/exif-photo-blog",
      "created": "2026.05.02"
    },
    {
      "title": "Sam Becker Photos",
      "link": "https://photos.sambecker.com/grid",
      "domain": "photos.sambecker.com",
      "tags": [],
      "note": "",
      "excerpt": "Random pictures, shared with 🤓 nerdy camera details via exif-photo-blog",
      "created": "2026.05.02"
    },
    {
      "title": "Afilmory - Where your photographs become exhibitions.",
      "link": "https://afilmory.art/",
      "domain": "afilmory.art",
      "tags": [],
      "note": "",
      "excerpt": "Where your photographs become exhibitions.",
      "created": "2026.05.02"
    },
    {
      "title": "Moxt | AI 原生的工作空间",
      "link": "https://moxt.ai/zh-CN",
      "domain": "moxt.ai",
      "tags": [],
      "note": "",
      "excerpt": "Moxt 是人与 AI Agents 可无缝协作的工作空间。你的 AI Agents 在这里安家，积累记忆和经验，全天候工作。",
      "created": "2026.04.30"
    },
    {
      "title": "Repairing the Ruins: Why AI Can’t Replace Education| National Catholic Register",
      "link": "https://www.ncregister.com/commentaries/schnell-repairing-the-ruins",
      "domain": "ncregister.com",
      "tags": [],
      "note": "",
      "excerpt": "COMMENTARY: In an era when AI can write anything, authentic education must go beyond the mere production of words.",
      "created": "2026.04.29"
    },
    {
      "title": "Mercury — Soul-Driven AI Agent with Permission Guardrails",
      "link": "https://mercury.cosmicstack.org/",
      "domain": "mercury.cosmicstack.org",
      "tags": [],
      "note": "",
      "excerpt": "The AI agent that asks before it acts. Permission guardrails, token efficiency, and full control with multi-provider onboarding.",
      "created": "2026.04.26"
    }
  ],
  "total": 177
}